CHANGELOG.rst
LICENSE.md
MANIFEST.in
README.rst
setup.cfg
setup.py
LazyHDF5.egg-info/PKG-INFO
LazyHDF5.egg-info/SOURCES.txt
LazyHDF5.egg-info/dependency_links.txt
LazyHDF5.egg-info/not-zip-safe
LazyHDF5.egg-info/requires.txt
LazyHDF5.egg-info/top_level.txt
lazy5/__init__.py
lazy5/alter.py
lazy5/config.py
lazy5/create.py
lazy5/inspect.py
lazy5/nonh5utils.py
lazy5/utils.py
lazy5/tests/__init__.py
lazy5/tests/test_alter.py
lazy5/tests/test_create.py
lazy5/tests/test_inspect.py
lazy5/tests/test_nonh5utils.py
lazy5/tests/test_ui.py
lazy5/tests/test_utils.py
lazy5/ui/QtHdfLoad.py
lazy5/ui/__init__.py
lazy5/ui/qt_HdfLoad.py
lazy5/ui/qt5/ui_HDFLoad.ui
lazy5/ui/qt5/ui_HdfLoad.ui